jupyter_anywidget_pglite/__init__.py
jupyter_anywidget_pglite/dbapi2.py
jupyter_anywidget_pglite/magics.py
jupyter_anywidget_pglite/sqlalchemy_api.py
jupyter_anywidget_pglite/static/audio.js
jupyter_anywidget_pglite/static/postgres.css
jupyter_anywidget_pglite/static/postgres.js
jupyter_anywidget_pglite/static/uuid.js
jupyter_anywidget_pglite-0.1.17.dist-info/METADATA
jupyter_anywidget_pglite-0.1.17.dist-info/WHEEL
jupyter_anywidget_pglite-0.1.17.dist-info/licenses/LICENSE
jupyter_anywidget_pglite-0.1.17.dist-info/RECORD
