Metadata-Version: 2.3
Name: jupyter_anywidget_pglite
Version: 0.1.17
Project-URL: Repository, https://github.com/innovationOUtside/jupyter_anywidget_pglite
Project-URL: Homepage, https://github.com/innovationOUtside/jupyter_anywidget_pglite
Author-email: Tony Hirst <tony.hirst@gmail.com>
License: MIT License
License-File: LICENSE
Requires-Dist: anywidget==0.9.13
Requires-Dist: pandas
Provides-Extra: dev
Requires-Dist: jupyterlab; extra == 'dev'
Requires-Dist: watchfiles; extra == 'dev'
